pystac_client/__init__.py
pystac_client/_utils.py
pystac_client/cli.py
pystac_client/client.py
pystac_client/collection_client.py
pystac_client/collection_search.py
pystac_client/conformance.py
pystac_client/errors.py
pystac_client/exceptions.py
pystac_client/free_text.py
pystac_client/item_search.py
pystac_client/mixins.py
pystac_client/py.typed
pystac_client/stac_api_io.py
pystac_client/version.py
pystac_client/warnings.py
pystac_client-0.8.5.dist-info/LICENSE
pystac_client-0.8.5.dist-info/METADATA
pystac_client-0.8.5.dist-info/WHEEL
pystac_client-0.8.5.dist-info/entry_points.txt
pystac_client-0.8.5.dist-info/top_level.txt
pystac_client-0.8.5.dist-info/RECORD
