Metadata-Version: 2.1
Name: pystac-client
Version: 0.8.5
Summary: Python library for working with SpatioTemporal Asset Catalog (STAC) APIs.
Author-email: Jon Duckworth <duckontheweb@gmail.com>, Matthew Hanson <matt.a.hanson@gmail.com>
Maintainer-email: Pete Gadomski <pete.gadomski@gmail.com>
License: Apache-2.0
Project-URL: homepage, https://github.com/stac-utils/pystac-client
Project-URL: documentation, https://pystac-client.readthedocs.io
Project-URL: repository, https://github.com/stac-utils/pystac-client.git
Project-URL: changelog, https://github.com/stac-utils/pystac-client/blob/main/CHANGELOG.md
Project-URL: discussions, https://github.com/radiantearth/stac-spec/discussions/categories/stac-software
Keywords: pystac,imagery,raster,catalog,STAC
Classifier: Programming Language :: Python
Classifier: Programming Language :: Python :: 3
Classifier: Programming Language :: Python :: 3.10
Classifier: Programming Language :: Python :: 3.11
Classifier: Programming Language :: Python :: 3.12
Classifier: Operating System :: OS Independent
Classifier: Natural Language :: English
Classifier: Development Status :: 4 - Beta
Classifier: Intended Audience :: Developers
Classifier: License :: OSI Approved :: Apache Software License
Classifier: Topic :: Scientific/Engineering :: GIS
Classifier: Topic :: Software Development :: Libraries
Classifier: Topic :: Software Development :: Libraries :: Python Modules
Requires-Python: >=3.10
License-File: LICENSE
Requires-Dist: requests>=2.28.2
Requires-Dist: pystac[validation]>=1.10.0
Requires-Dist: python-dateutil>=2.8.2
Provides-Extra: dev
Requires-Dist: black~=24.0; extra == "dev"
Requires-Dist: codespell~=2.3.0; extra == "dev"
Requires-Dist: coverage~=7.2; extra == "dev"
Requires-Dist: doc8~=1.1.1; extra == "dev"
Requires-Dist: importlib-metadata~=8.0; extra == "dev"
Requires-Dist: mypy~=1.2; extra == "dev"
Requires-Dist: orjson~=3.8; extra == "dev"
Requires-Dist: pre-commit~=4.0; extra == "dev"
Requires-Dist: pytest-benchmark~=4.0.0; extra == "dev"
Requires-Dist: pytest-console-scripts~=1.4.0; extra == "dev"
Requires-Dist: pytest-cov~=5.0; extra == "dev"
Requires-Dist: pytest-recording~=0.13; extra == "dev"
Requires-Dist: pytest~=8.0; extra == "dev"
Requires-Dist: recommonmark~=0.7.1; extra == "dev"
Requires-Dist: requests-mock~=1.12; extra == "dev"
Requires-Dist: ruff==0.7.0; extra == "dev"
Requires-Dist: tomli~=2.0; python_version < "3.11" and extra == "dev"
Requires-Dist: types-python-dateutil<2.10.0,>=2.8.19; extra == "dev"
Requires-Dist: types-requests~=2.32.0; extra == "dev"
Requires-Dist: urllib3~=2.0; extra == "dev"
Provides-Extra: docs
Requires-Dist: Sphinx~=8.0; extra == "docs"
Requires-Dist: boto3~=1.26; extra == "docs"
Requires-Dist: cartopy~=0.21; extra == "docs"
Requires-Dist: geojson~=3.1.0; extra == "docs"
Requires-Dist: geopandas~=1.0.0; extra == "docs"
Requires-Dist: geoviews~=1.9; extra == "docs"
Requires-Dist: hvplot~=0.11.0; extra == "docs"
Requires-Dist: ipykernel~=6.22; extra == "docs"
Requires-Dist: ipython~=8.12; extra == "docs"
Requires-Dist: jinja2<4.0; extra == "docs"
Requires-Dist: matplotlib~=3.8; extra == "docs"
Requires-Dist: myst-parser~=4.0; extra == "docs"
Requires-Dist: nbsphinx~=0.9; extra == "docs"
Requires-Dist: pydata-sphinx-theme~=0.13; extra == "docs"
Requires-Dist: pygeoif~=1.0; extra == "docs"
Requires-Dist: scipy~=1.10; extra == "docs"
Requires-Dist: sphinxcontrib-fulltoc~=1.2; extra == "docs"
